src/gray_counter.sv
module gray_counter #(
    parameter WIDTH = 4
)(
    input logic clk,
    input logic rst,
    input logic en,
    output logic [WIDTH-1:0] gray_count,
    output logic [WIDTH-1:0] binary_count
);

always_ff@(posedge clk, negedge rst) begin
    if(!rst) begin
        binary_count <= '0;
    end else begin
        if(en) begin
            binary_count <= binary_count + 1;
        end
    end
end

assign gray_count = binary_count ^ (binary_count >> 1);

endmodule

tb/gray_counter_tb.sv
module gray_counter_tb;

    logic clk;
    logic rst;
    logic en;
    logic [3:0] gray_count;
    logic [3:0] binary_count;
    logic [3:0] prev_gray;

    initial begin
        clk = 0;
        forever #10 clk = ~clk;
    end

    gray_counter #(
        .WIDTH(4)
    ) dut (
        .clk(clk),
        .rst(rst),
        .en(en),
        .gray_count(gray_count),
        .binary_count(binary_count)
    );

    initial begin
        $dumpfile("sim/gray_counter.vcd");
        $dumpvars(0, gray_counter_tb);

        rst = 0;
        en  = 0;
        @(posedge clk); #1;
        @(posedge clk); #1;
        rst = 1;
        en  = 1;

        for (int i = 0; i < 20; i++) begin
            @(posedge clk);
            #1;

            if (i != 0) begin
                if ($countones(prev_gray ^ gray_count) == 1) begin
                    $display("NICE, single bit change at i=%0d, gray=%b", i, gray_count);
                end else begin
                    $display("NOOO, bad transition at i=%0d, gray=%b", i, gray_count);
                end
            end

            prev_gray = gray_count;
        end

        if (binary_count == 4) begin
            $display("YAY!");
        end else begin
            $display("NAY!");
        end

        // NEW TEST 1: reset priority over enable
        // Assert both rst=0 (active) and en=1 at the same time.
        // Reset must win — binary_count should go to 0, not increment.
        en  = 1;
        rst = 0;
        @(posedge clk); #1;

        if (binary_count == '0) begin
            $display("NICE, reset correctly took priority over enable, binary_count=%0d", binary_count);
        end else begin
            $display("NOOO, reset did NOT take priority, binary_count=%0d", binary_count);
        end

        rst = 1;

        $finish;
    end

endmodule

sim/gray_counter.vcd
$date
	Wed Sep 16 16:07:10 2026
$end
$version
	Icarus Verilog
$end
$timescale
	1s
$end
$scope module gray_counter_tb $end
$var wire 4 ! gray_count [3:0] $end
$var wire 4 " binary_count [3:0] $end
$var reg 1 # clk $end
$var reg 1 $ en $end
$var reg 4 % prev_gray [3:0] $end
$var reg 1 & rst $end
$scope module dut $end
$var wire 1 # clk $end
$var wire 1 $ en $end
$var wire 4 ' gray_count [3:0] $end
$var wire 1 & rst $end
$var parameter 32 ( WIDTH $end
$var reg 4 ) binary_count [3:0] $end
$upscope $end
$scope begin $ivl_for_loop0 $end
$var integer 32 * i [31:0] $end
$upscope $end
$upscope $end
$enddefinitions $end
$comment Show the parameter values. $end
$dumpall
b100 (
$end
#0
$dumpvars
b0 *
b0 )
b0 '
0&
bx %
0$
0#
b0 "
b0 !
$end
#10
1#
#20
0#
#30
1#
#31
1$
1&
#40
0#
#50
b1 !
b1 '
b1 "
b1 )
1#
#51
b1 *
b1 %
#60
0#
#70
b11 !
b11 '
b10 "
b10 )
1#
#71
b10 *
b11 %
#80
0#
#90
b10 !
b10 '
b11 "
b11 )
1#
#91
b11 *
b10 %
#100
0#
#110
b110 !
b110 '
b100 "
b100 )
1#
#111
b100 *
b110 %
#120
0#
#130
b111 !
b111 '
b101 "
b101 )
1#
#131
b101 *
b111 %
#140
0#
#150
b101 !
b101 '
b110 "
b110 )
1#
#151
b110 *
b101 %
#160
0#
#170
b100 !
b100 '
b111 "
b111 )
1#
#171
b111 *
b100 %
#180
0#
#190
b1100 !
b1100 '
b1000 "
b1000 )
1#
#191
b1000 *
b1100 %
#200
0#
#210
b1101 !
b1101 '
b1001 "
b1001 )
1#
#211
b1001 *
b1101 %
#220
0#
#230
b1111 !
b1111 '
b1010 "
b1010 )
1#
#231
b1010 *
b1111 %
#240
0#
#250
b1110 !
b1110 '
b1011 "
b1011 )
1#
#251
b1011 *
b1110 %
#260
0#
#270
b1010 !
b1010 '
b1100 "
b1100 )
1#
#271
b1100 *
b1010 %
#280
0#
#290
b1011 !
b1011 '
b1101 "
b1101 )
1#
#291
b1101 *
b1011 %
#300
0#
#310
b1001 !
b1001 '
b1110 "
b1110 )
1#
#311
b1110 *
b1001 %
#320
0#
#330
b1000 !
b1000 '
b1111 "
b1111 )
1#
#331
b1111 *
b1000 %
#340
0#
#350
b0 !
b0 '
b0 "
b0 )
1#
#351
b10000 *
b0 %
#360
0#
#370
b1 !
b1 '
b1 "
b1 )
1#
#371
b10001 *
b1 %
#380
0#
#390
b11 !
b11 '
b10 "
b10 )
1#
#391
b10010 *
b11 %
#400
0#
#410
b10 !
b10 '
b11 "
b11 )
1#
#411
b10011 *
b10 %
#420
0#
#430
b110 !
b110 '
b100 "
b100 )
1#
#431
b0 !
b0 '
b0 "
b0 )
0&
b10100 *
b110 %
#440
0#
#450
1#
#451
1&
