src/sync_2ff.sv
module sync_2ff #(
    parameter WIDTH = 4
)(
    input logic[WIDTH-1:0] gray_value,
    input logic clk,
    input logic rst,
    output logic[WIDTH-1:0] cross_gray_value
);
//body

logic[WIDTH-1:0] gray_value_intermediate;

always_ff@(posedge clk, negedge rst) begin

    if(!rst) begin
        gray_value_intermediate <= '0;
        cross_gray_value <= '0;
    end
    else begin
        gray_value_intermediate <= gray_value;
        cross_gray_value <= gray_value_intermediate;
    end

end

endmodule

tb/sync_2ff_tb.sv
module sync_2ff_tb;

    logic clk;
    logic rst;
    logic [3:0] gray_value;
    logic [3:0] cross_gray_value;

    logic [3:0] expected_stage1;
    logic [3:0] expected_stage2;

    sync_2ff #(
        .WIDTH(4)
    ) dut (
        .gray_value(gray_value),
        .clk(clk),
        .rst(rst),
        .cross_gray_value(cross_gray_value)
    );

    initial begin
        clk = 0;
        forever #10 clk = ~clk;
    end

    initial begin
        $dumpfile("sim/sync_2ff.vcd");
        $dumpvars(0, sync_2ff_tb);

        rst = 0;
        gray_value = 4'b0000;
        @(posedge clk); #1;
        @(posedge clk); #1;
        rst = 1;

        expected_stage1 = '0;
        expected_stage2 = '0;

        gray_value = 4'b0001;
        #7;
        gray_value = 4'b0011;

        for (int i = 0; i < 10; i++) begin
            @(posedge clk); #1;

            expected_stage2 = expected_stage1;
            expected_stage1 = gray_value;

            if (cross_gray_value !== expected_stage2) begin
                $display("NOOO, mismatch at i=%0d: expected=%b got=%b", i, expected_stage2, cross_gray_value);
            end else begin
                $display("NICE, i=%0d cross_gray_value=%b matches expected", i, cross_gray_value);
            end
        end

        $finish;
    end

endmodule

sim/sync_2ff.vcd
$date
	Tue Sep 15 14:45:00 2026
$end
$version
	Icarus Verilog
$end
$timescale
	1s
$end
$scope module sync_2ff_tb $end
$var wire 4 ! cross_gray_value [3:0] $end
$var reg 1 " clk $end
$var reg 4 # expected_stage1 [3:0] $end
$var reg 4 $ expected_stage2 [3:0] $end
$var reg 4 % gray_value [3:0] $end
$var reg 1 & rst $end
$scope module dut $end
$var wire 1 " clk $end
$var wire 4 ' gray_value [3:0] $end
$var wire 1 & rst $end
$var parameter 32 ( WIDTH $end
$var reg 4 ) cross_gray_value [3:0] $end
$var reg 4 * gray_value_intermediate [3:0] $end
$upscope $end
$scope begin $ivl_for_loop0 $end
$var integer 32 + i [31:0] $end
$upscope $end
$upscope $end
$enddefinitions $end
$comment Show the parameter values. $end
$dumpall
b100 (
$end
#0
$dumpvars
b0 +
b0 *
b0 )
b0 '
0&
b0 %
bx $
bx #
0"
b0 !
$end
#10
1"
#20
0"
#30
1"
#31
b1 %
b1 '
b0 $
b0 #
1&
#38
b11 %
b11 '
#40
0"
#50
b11 *
1"
#51
b1 +
b11 #
#60
0"
#70
b11 !
b11 )
1"
#71
b10 +
b11 $
#80
0"
#90
1"
#91
b11 +
#100
0"
#110
1"
#111
b100 +
#120
0"
#130
1"
#131
b101 +
#140
0"
#150
1"
#151
b110 +
#160
0"
#170
1"
#171
b111 +
#180
0"
#190
1"
#191
b1000 +
#200
0"
#210
1"
#211
b1001 +
#220
0"
#230
1"
#231
b1010 +
